pyElectoral/CNE.py
pyElectoral/Data.py
pyElectoral/Parse.py
pyElectoral/__init__.py
pyElectoral-1.0.5.dist-info/LICENSE
pyElectoral-1.0.5.dist-info/METADATA
pyElectoral-1.0.5.dist-info/WHEEL
pyElectoral-1.0.5.dist-info/top_level.txt
pyElectoral-1.0.5.dist-info/RECORD
