Metadata-Version: 2.1
Name: pyElectoral
Version: 1.0.5
Summary: Libreria Python para consultas al CNE de Venezuela con GUI integradas
Home-page: https://rep98.vzlaweb.com
Author: Robert Pérez
Author-email: delfinmundo@gmail.com
License: MIT
License-File: LICENSE
Requires-Dist: requests
Requires-Dist: bs4
